bayesnetwork/__init__.py
bayesnetwork/bayesnetwork.py
bayesnetwork-0.1.0.dist-info/METADATA
bayesnetwork-0.1.0.dist-info/WHEEL
bayesnetwork-0.1.0.dist-info/entry_points.txt
bayesnetwork-0.1.0.dist-info/top_level.txt
bayesnetwork-0.1.0.dist-info/RECORD
