Metadata-Version: 2.1
Name: bayesnetwork
Version: 0.1.0
Summary: Libreria de redes bayesianas para inferencia probabilistica.
Home-page: https://github.com/MaJu502/Inferencia-probabilistica
Author: Marco Jurado
Author-email: marcojuradovelasquez2001@gmail.com
License: MIT
Requires-Python: >=3.6
